{
  "notes_md": "**ăn trộm** means *to steal* (to take something secretly that isn’t yours). It’s a verb, not a noun — the person is **kẻ trộm** or **tên trộm**.\n\nUse it with a direct object: what was stolen, and often **của + someone** to say whose it was.  \n\nYou can also say **đi ăn trộm** = go out stealing.  \nClose synonym: **ăn cắp** (very similar; “ăn cắp” is heard a bit more in the North).",
  "rank": 423,
  "choices": [
    "ăn trưa",
    "ăn trộm",
    "ăn kem"
  ],
  "addedReason": "steal/thief",
  "exampleSentencesAudioUrlsNorthern": [
    "northern_1.mp3",
    "northern_2.mp3",
    "northern_3.mp3"
  ],
  "word": "ăn trộm",
  "originalFrequency": 0.0221,
  "createdAt": "2025-07-21T11:12:52.742Z",
  "exampleSentencesAudioUrls": [
    "southern_1.mp3",
    "southern_2.mp3",
    "southern_3.mp3"
  ],
  "language": "vi",
  "source": "frequency_analysis",
  "definition": "steal / thief",
  "exampleSentencesTranslated": [
    "I just saw a thief run across this street.",
    "The police are looking for the thief who took your wallet.",
    "Everyone should be careful of a thief when going to a crowded market."
  ],
  "updatedAt": "2026-03-03T07:04:37.578Z",
  "exampleSentences": [
    "Anh vừa thấy một tên ăn trộm chạy qua con phố này.",
    "Cảnh sát đang tìm kiếm kẻ ăn trộm đã lấy ví của chị.",
    "Mọi người nên cảnh giác với kẻ ăn trộm khi đi chợ đông người."
  ],
  "originalCount": 25,
  "notes": "ăn trộm means to steal (to take something secretly that isn’t yours). It’s a verb, not a noun — the person is kẻ trộm or tên trộm.\n\nUse it with a direct object: what was stolen, and often của + someone to say whose it was.  \n\nYou can also say đi ăn trộm = go out stealing.  \nClose synonym: ăn cắp (very similar; “ăn cắp” is heard a bit more in the North).",
  "_id": "fIZqkwnCyGJIpuOsLy5Q",
  "level": "B1",
  "topic": "Crime & Law"
}