{
  "choices": [
    "mơ ước",
    "hy vọng",
    "kế hoạch"
  ],
  "notes": "mơ ước = a dream, something you really hope to have or become in the future. It’s stronger and more emotional than just a plan.\n\nIt’s a noun. You can count it: một mơ ước, nhiều mơ ước.  \nOften used with verbs like có, theo đuổi, thực hiện, giữ (have, pursue, realize, hold onto a dream).\n\nClose words: ước mơ (very similar, slightly more common in speech), khát vọng (stronger, more intense ambition).",
  "rank": 1007,
  "originalFrequency": 0.0097,
  "exampleSentencesTranslated": [
    "Since childhood, I have had a dream of becoming a doctor to help people.",
    "He always tries his best to achieve his dream.",
    "She shared her dream with her family last night."
  ],
  "word": "mơ ước",
  "updatedAt": "2026-03-03T08:03:16.493Z",
  "exampleSentencesAudioUrls": [
    "southern_1.mp3",
    "southern_2.mp3",
    "southern_3.mp3"
  ],
  "addedReason": "common verb",
  "exampleSentencesAudioUrlsNorthern": [
    "northern_1.mp3",
    "northern_2.mp3",
    "northern_3.mp3"
  ],
  "source": "frequency_analysis",
  "definition": "dream",
  "createdAt": "2025-07-21T12:02:18.788Z",
  "language": "vi",
  "originalCount": 11,
  "exampleSentences": [
    "Từ nhỏ, em đã có mơ ước trở thành bác sĩ để giúp đỡ mọi người.",
    "Anh luôn cố gắng hết mình để thực hiện mơ ước của mình.",
    "Chị ấy chia sẻ mơ ước của mình với gia đình vào tối qua."
  ],
  "notes_md": "**mơ ước** = a dream, something you really hope to have or become in the future. It’s stronger and more emotional than just a plan.\n\nIt’s a **noun**. You can count it: *một mơ ước, nhiều mơ ước*.  \nOften used with verbs like **có**, **theo đuổi**, **thực hiện**, **giữ** (have, pursue, realize, hold onto a dream).\n\n\nClose words: **ước mơ** (very similar, slightly more common in speech), **khát vọng** (stronger, more intense ambition).",
  "_id": "SPwB4OKOOfplmb7iZW8c"
}