{
  "exampleSentences": [
    "Anh ấy đã cố tình đến trễ để tránh buổi họp quan trọng.",
    "Chị không nghĩ em làm sai sót đó cố tình đâu.",
    "Họ nói lời đó cố tình để làm em buồn."
  ],
  "exampleSentencesAudioUrls": [
    "southern_1.mp3",
    "southern_2.mp3",
    "southern_3.mp3"
  ],
  "language": "vi",
  "rank": 844,
  "originalFrequency": 0.0115,
  "updatedAt": "2026-03-03T07:46:20.242Z",
  "choices": [
    "cố gắng",
    "cố tình",
    "tình cờ"
  ],
  "exampleSentencesTranslated": [
    "He arrived late on purpose to avoid the important meeting.",
    "I don't think you made that mistake on purpose.",
    "They said those words on purpose to make you sad."
  ],
  "notes": "cố tình = on purpose, intentionally. It means someone deliberately does something, not by accident.\n\nIt usually comes before a verb to show intention.  \n\nIt often carries a slightly negative feeling, like the action caused trouble or hurt someone.  \nOpposite: vô tình (accidentally) — easy pair to remember.",
  "addedReason": "common verb phrase",
  "definition": "on purpose",
  "createdAt": "2025-07-21T11:47:26.928Z",
  "originalCount": 13,
  "word": "cố tình",
  "exampleSentencesAudioUrlsNorthern": [
    "northern_1.mp3",
    "northern_2.mp3",
    "northern_3.mp3"
  ],
  "source": "frequency_analysis",
  "notes_md": "**cố tình** = on purpose, intentionally. It means someone *deliberately* does something, not by accident.\n\nIt usually comes before a verb to show intention.  \n\nIt often carries a slightly negative feeling, like the action caused trouble or hurt someone.  \nOpposite: **vô tình** (accidentally) — easy pair to remember.",
  "flashcard": {
    "definitions": {
      "vi": "Trạng từ/Động từ chỉ hành động được thực hiện một cách có chủ ý, không phải do vô ý.",
      "en": "On purpose; intentionally; deliberately (often with a negative connotation).",
      "es": "A propósito; intencionalmente."
    },
    "audioUrl": "flashcard.mp3",
    "translations": {
      "vi": "cố tình",
      "en": "on purpose",
      "es": "a propósito"
    },
    "createdAt": "2025-03-12T13:00:00.000Z",
    "example": {
      "vi": "Cố tình đến trễ.",
      "en": "Arriving late on purpose.",
      "es": "Llegar tarde a propósito."
    }
  },
  "multiChoiceQuiz": {
    "type": "multiChoiceQuiz",
    "id": "e5f6g7h8-a1b2-c3d4-e5f6-g7h8i9j0k1l2",
    "audioUrl": "multi_choice.mp3",
    "createdAt": "2025-03-12T13:00:00.000Z",
    "updatedAt": "2025-03-12T13:00:00.000Z",
    "content": {
      "word": "cố tình",
      "language": "vi",
      "sentence": "Anh ấy đã ___ đến trễ để tránh buổi họp quan trọng.",
      "choices": [
        "cố gắng",
        "cố tình",
        "tình cờ"
      ],
      "answer": "cố tình",
      "translation": {
        "en": "He arrived late on purpose to avoid the important meeting."
      },
      "translatedAnswer": {
        "en": "on purpose"
      }
    }
  },
  "fillBlankQuiz": {
    "type": "fillBlankQuiz",
    "id": "f6g7h8i9-a1b2-c3d4-e5f6-g7h8i9j0k1l2",
    "audioUrl": "fill_blank.mp3",
    "createdAt": "2025-03-12T13:00:00.000Z",
    "updatedAt": "2025-03-12T13:00:00.000Z",
    "content": {
      "word": "cố tình",
      "language": "vi",
      "sentence": "Họ nói lời đó ___ để làm em buồn.",
      "answer": "cố tình",
      "translation": {
        "en": "They said those words on purpose to make you sad."
      },
      "translatedAnswer": {
        "en": "on purpose"
      }
    }
  },
  "_id": "Lycw0O4HFyEMXj576v6S",
  "level": "B2",
  "topic": "Actions & Behaviors"
}