{
  "originalFrequency": 0.0194,
  "choices": [
    "xe lửa",
    "nhà",
    "ga"
  ],
  "originalCount": 22,
  "exampleSentences": [
    "Anh sẽ đón em ở ga lúc bảy giờ tối nay.",
    "Chị thường uống cà phê gần ga vào buổi sáng.",
    "Em có biết ga này cách trung tâm thành phố bao xa không?"
  ],
  "exampleSentencesAudioUrls": [
    "southern_1.mp3",
    "southern_2.mp3",
    "southern_3.mp3"
  ],
  "notes": "ga = station, usually a train station. Think “railway station” first.\n\nIt’s a noun. Often used in ga tàu / ga xe lửa / ga metro. You’ll also hear nhà ga for the station building itself.\n\nVery common second meaning: ga = the accelerator in a vehicle. In driving, đạp ga means press the gas pedal (opposite idea: phanh = brake).",
  "definition": "station",
  "rank": 484,
  "exampleSentencesAudioUrlsNorthern": [
    "northern_1.mp3",
    "northern_2.mp3",
    "northern_3.mp3"
  ],
  "notes_md": "**ga** = station, usually a train station. Think “railway station” first.\n\nIt’s a noun. Often used in **ga tàu / ga xe lửa / ga metro**. You’ll also hear **nhà ga** for the station building itself.\n\n\nVery common second meaning: **ga** = the accelerator in a vehicle. In driving, **đạp ga** means press the gas pedal (opposite idea: phanh = brake).",
  "language": "vi",
  "exampleSentencesTranslated": [
    "I will pick you up at the station at seven tonight.",
    "She usually drinks coffee near the station in the morning.",
    "Do you know how far this station is from the city center?"
  ],
  "addedReason": "station/railway",
  "updatedAt": "2026-03-03T07:10:38.164Z",
  "source": "frequency_analysis",
  "word": "ga",
  "createdAt": "2025-07-21T11:17:01.528Z",
  "flashcard": {
    "definitions": {
      "vi": "Nơi tàu dừng để đón, trả khách.",
      "en": "Station; railway station.",
      "es": "Estación."
    },
    "audioUrl": "flashcard.mp3",
    "translations": {
      "vi": "ga",
      "en": "station",
      "es": "estación"
    },
    "createdAt": "2025-03-12T13:00:00.000Z",
    "example": {
      "vi": "Gặp nhau ở ga tàu nhé.",
      "en": "Let's meet at the train station.",
      "es": "Nos vemos trong la estación de tren."
    }
  },
  "multiChoiceQuiz": {
    "type": "multiChoiceQuiz",
    "id": "c8d9e0f1-1234-5678-9012-34567890abcd",
    "audioUrl": "multi_choice.mp3",
    "createdAt": "2025-03-12T13:00:00.000Z",
    "updatedAt": "2025-03-12T13:00:00.000Z",
    "content": {
      "word": "ga",
      "language": "vi",
      "sentence": "Tôi đang đứng đợi ở ___.",
      "choices": [
        "ga",
        "nhà",
        "trường"
      ],
      "answer": "ga",
      "translation": {
        "en": "I am standing waiting at the station."
      },
      "translatedAnswer": {
        "en": "station"
      }
    }
  },
  "fillBlankQuiz": {
    "type": "fillBlankQuiz",
    "id": "d9e0f1g2-1234-5678-9012-34567890abcd",
    "audioUrl": "fill_blank.mp3",
    "createdAt": "2025-03-12T13:00:00.000Z",
    "updatedAt": "2025-03-12T13:00:00.000Z",
    "content": {
      "word": "ga",
      "language": "vi",
      "sentence": "Nhà ___ rất đông người.",
      "answer": "ga",
      "translation": {
        "en": "The station building is very crowded."
      },
      "translatedAnswer": {
        "en": "station"
      }
    }
  },
  "_id": "j0Q0sp5HitQ2dzuHVPAn",
  "level": "A2",
  "topic": "Places & Locations"
}