{
  "definition": "approve",
  "notes_md": "**duyệt** = to approve, to give official permission after checking something. It’s often used in work or formal situations.\n\nYou **duyệt** plans, reports, applications, budgets, contracts — usually documents or proposals that need a higher-up’s OK. The subject is often a boss, manager, or authority.\n\n\nClose synonym: **phê duyệt** (more formal, stronger official tone).",
  "createdAt": "2025-01-27T21:23:43.157Z",
  "flashcard": {
    "audioUrl": "flashcard.mp3",
    "createdAt": "2025-01-28T12:39:33.934Z",
    "definitions": {
      "en": "To review or examine something carefully.",
      "es": "Revisar o examinar algo cuidadosamente.",
      "vi": "Xem xét hoặc kiểm tra một cái gì đó một cách cẩn thận."
    },
    "example": {
      "en": "I reviewed the document before sending it.",
      "es": "Revisé el documento antes de enviarlo.",
      "vi": "Tôi đã duyệt qua tài liệu trước khi gửi."
    },
    "translations": {
      "en": "review",
      "es": "revisar",
      "vi": "duyệt"
    }
  },
  "fillBlankQuiz": {
    "audioUrl": "fill_blank.mp3",
    "type": "fillBlankQuiz",
    "createdAt": "2025-03-12T15:06:49.434Z",
    "updatedAt": "2025-03-12T15:06:49.434Z",
    "content": {
      "sentence": "Tôi cần ___ bài báo này.",
      "word": "duyệt",
      "language": "vi",
      "answer": "duyệt",
      "translatedAnswer": {
        "en": "review"
      },
      "choices": [],
      "translation": {
        "en": "I need to review this article."
      }
    },
    "id": "0495e7d0-2ca2-4e9d-9766-c46010866ffd"
  },
  "exampleSentencesAudioUrls": [
    "southern_1.mp3",
    "southern_2.mp3",
    "southern_3.mp3"
  ],
  "updatedAt": "2026-03-03T10:22:53.007Z",
  "exampleSentencesTranslated": [
    "I will approve this plan before sending it to the director.",
    "She approved my leave request this morning.",
    "I need the boss to approve this report before submitting it."
  ],
  "exampleSentences": [
    "Anh sẽ duyệt kế hoạch này trước khi gửi cho giám đốc.",
    "Chị đã duyệt đơn xin nghỉ phép của em sáng nay rồi.",
    "Em cần sếp duyệt bản báo cáo này trước khi nộp."
  ],
  "notes": "duyệt = to approve, to give official permission after checking something. It’s often used in work or formal situations.\n\nYou duyệt plans, reports, applications, budgets, contracts — usually documents or proposals that need a higher-up’s OK. The subject is often a boss, manager, or authority.\n\nClose synonym: phê duyệt (more formal, stronger official tone).",
  "word": "duyệt",
  "multiChoiceQuiz": {
    "id": "051e7d1b-c89a-449d-8389-13e6b5e10321",
    "type": "multiChoiceQuiz",
    "audioUrl": "multi_choice.mp3",
    "createdAt": "2025-03-12T15:06:49.434Z",
    "updatedAt": "2025-03-12T15:06:49.434Z",
    "content": {
      "choices": [
        "duyệt",
        "đọc",
        "sửa"
      ],
      "translatedAnswer": {
        "en": "review"
      },
      "translation": {
        "en": "We need to review the new documents."
      },
      "sentence": "Chúng ta cần ___ tài liệu mới.",
      "word": "duyệt",
      "language": "vi",
      "hint": "d___t",
      "answer": "duyệt"
    }
  },
  "exampleSentencesAudioUrlsNorthern": [
    "northern_1.mp3",
    "northern_2.mp3",
    "northern_3.mp3"
  ],
  "rank": 2311,
  "choices": [
    "duyệt",
    "từ chối",
    "hoãn"
  ],
  "_id": "YrhUvaWPYsnDnIGLsscH",
  "level": "B2",
  "topic": "Work & Education"
}