{
  "exampleSentencesAudioUrlsNorthern": [
    "northern_1.mp3",
    "northern_2.mp3",
    "northern_3.mp3"
  ],
  "language": "vi",
  "notes_md": "**tin vui** = good news, something positive you’re happy to hear. It’s a noun.\n\nYou usually use it with verbs like **nhận**, **nghe**, **báo**, **mang đến** + tin vui. No classifier needed in most cases; just say *tin vui* as a chunk.\n\nIt often appears in situations about work, family, health, exams, or big life updates.\n\nSynonym to remember: **tin tốt** (more neutral). Opposite: **tin buồn** (sad news).",
  "exampleSentencesTranslated": [
    "I just received good news from the company about the promotion.",
    "She has good news to share with the whole family tonight.",
    "After many days of waiting, I finally heard good news from the hospital."
  ],
  "addedReason": "good news",
  "createdAt": "2025-07-21T11:37:17.793Z",
  "word": "tin vui",
  "source": "frequency_analysis",
  "updatedAt": "2026-03-03T07:34:20.910Z",
  "originalCount": 15,
  "originalFrequency": 0.0132,
  "choices": [
    "tin buồn",
    "tin vui",
    "tin cũ"
  ],
  "exampleSentencesAudioUrls": [
    "southern_1.mp3",
    "southern_2.mp3",
    "southern_3.mp3"
  ],
  "exampleSentences": [
    "Anh vừa nhận được tin vui từ công ty về việc thăng chức.",
    "Chị có tin vui muốn chia sẻ với cả nhà vào tối nay.",
    "Sau nhiều ngày chờ đợi, cuối cùng em cũng nghe tin vui từ bệnh viện."
  ],
  "definition": "good news",
  "notes": "tin vui = good news, something positive you’re happy to hear. It’s a noun.\n\nYou usually use it with verbs like nhận, nghe, báo, mang đến + tin vui. No classifier needed in most cases; just say tin vui as a chunk.\n\nIt often appears in situations about work, family, health, exams, or big life updates.\n\nSynonym to remember: tin tốt (more neutral). Opposite: tin buồn (sad news).",
  "rank": 726,
  "flashcard": {
    "definitions": {
      "vi": "Thông tin tốt lành mang lại cảm giác vui vẻ, hạnh phúc.",
      "en": "Good news; positive information.",
      "es": "Buenas noticias."
    },
    "audioUrl": "flashcard.mp3",
    "translations": {
      "vi": "tin vui",
      "en": "good news",
      "es": "buenas noticias"
    },
    "createdAt": "2025-03-12T13:00:00.000Z",
    "example": {
      "vi": "Tôi có một tin vui cho bạn.",
      "en": "I have some good news for you.",
      "es": "Tengo una buena noticia para ti."
    }
  },
  "multiChoiceQuiz": {
    "type": "multiChoiceQuiz",
    "id": "g9h0i1j2-1234-5678-9012-34567890abcd",
    "audioUrl": "multi_choice.mp3",
    "createdAt": "2025-03-12T13:00:00.000Z",
    "updatedAt": "2025-03-12T13:00:00.000Z",
    "content": {
      "word": "tin vui",
      "language": "vi",
      "sentence": "Anh vừa nhận được ___ từ công ty về việc thăng chức.",
      "choices": [
        "tin buồn",
        "tin vui",
        "tin cũ"
      ],
      "answer": "tin vui",
      "translation": {
        "en": "I just received good news from the company about the promotion."
      },
      "translatedAnswer": {
        "en": "good news"
      }
    }
  },
  "fillBlankQuiz": {
    "type": "fillBlankQuiz",
    "id": "h0i1j2k3-1234-5678-9012-34567890abcd",
    "audioUrl": "fill_blank.mp3",
    "createdAt": "2025-03-12T13:00:00.000Z",
    "updatedAt": "2025-03-12T13:00:00.000Z",
    "content": {
      "word": "tin vui",
      "language": "vi",
      "sentence": "Chị có ___ muốn chia sẻ với cả nhà.",
      "answer": "tin vui",
      "translation": {
        "en": "She has good news to share with everyone."
      },
      "translatedAnswer": {
        "en": "good news"
      }
    }
  },
  "_id": "hwFucQoHj9zhfhPonP2p",
  "level": "A2",
  "topic": "Emotions & Feelings"
}